flask_filter/__init__.py
flask_filter/base.py
flask_filter/query_filter.py
flask_filter/schemas.py
flask_filter/filters/__init__.py
flask_filter/filters/filters.py
Flask_Filter-0.1.2a3.dist-info/LICENSE
Flask_Filter-0.1.2a3.dist-info/METADATA
Flask_Filter-0.1.2a3.dist-info/WHEEL
Flask_Filter-0.1.2a3.dist-info/top_level.txt
Flask_Filter-0.1.2a3.dist-info/RECORD
