Metadata-Version: 2.1
Name: Flask-Filter
Version: 0.1.2a3
Summary: A Flask extension for creating standard resource searches
Home-page: https://github.com/exleym/Flask-Filter 
Author: Exley McCormick
Author-email: exleym@gmail.com
License: Creative Commons Attribution-Noncommercial-Share Alike license
License-File: LICENSE
Requires-Dist: flask
Requires-Dist: marshmallow
Requires-Dist: sqlalchemy
Requires-Dist: Flask-SQLAlchemy
